cjm_torchvision_tfms/__init__.py
cjm_torchvision_tfms/_modidx.py
cjm_torchvision_tfms/collate_funcs.py
cjm_torchvision_tfms/core.py
cjm_torchvision_tfms/transforms.py
cjm_torchvision_tfms/utils.py
cjm_torchvision_tfms-0.0.26.dist-info/LICENSE
cjm_torchvision_tfms-0.0.26.dist-info/METADATA
cjm_torchvision_tfms-0.0.26.dist-info/WHEEL
cjm_torchvision_tfms-0.0.26.dist-info/entry_points.txt
cjm_torchvision_tfms-0.0.26.dist-info/top_level.txt
cjm_torchvision_tfms-0.0.26.dist-info/RECORD
