Metadata-Version: 2.2
Name: cjm-torchvision-tfms
Version: 0.0.26
Summary: Some custom Torchvision tranforms.
Home-page: https://github.com/cj-mills/cjm-torchvision-tfms
Author: Christian Mills
Author-email: millscj@protonmail.com
License: Apache Software License 2.0
Keywords: nbdev jupyter notebook python
Classifier: Development Status :: 4 - Beta
Classifier: Intended Audience :: Developers
Classifier: Natural Language :: English
Classifier: Programming Language :: Python :: 3.10
Classifier: Programming Language :: Python :: 3.11
Classifier: License :: OSI Approved :: Apache Software License
Requires-Python: >=3.10
License-File: LICENSE
Requires-Dist: torch
Requires-Dist: numpy
Requires-Dist: torchvision>=0.21.0
Requires-Dist: cjm_pytorch_utils
Requires-Dist: cjm_pil_utils
Requires-Dist: cjm_psl_utils
Requires-Dist: opencv-python
Provides-Extra: dev
Dynamic: author
Dynamic: author-email
Dynamic: classifier
Dynamic: description
Dynamic: description-content-type
Dynamic: home-page
Dynamic: keywords
Dynamic: license
Dynamic: provides-extra
Dynamic: requires-dist
Dynamic: requires-python
Dynamic: summary
